{
    "_comment": "Originally made by @TenebrisNoctua. Modified by @Average_FreeTooPlay",
    "Name": "UI",
    "Controls": [
        {
            "Id": "GUI",
            "Type": "SplitButton",
            "ShowSettingOptions": true,
            "Setting": {
                "PluginId": "BuilderTools",
                "DataModel": "Standalone",
                "ItemId": "InsertGui",
                "Category": "Settings"
            }
        },
        {
            "Size": "Large",
            "Type": "Separator"
        },
        {
            "Id": "Frame",
            "Type": "SplitButton",
            "Setting": {
                "PluginId": "BuilderTools",
                "DataModel": "Standalone",
                "Category": "Settings",
                "ItemId": "InsertUIFrame"
            },
            "ShowSettingOptions": true
        },
        {
            "Id": "864d079f-84de-4ad2-8995-966bbf9eb8f8",
            "Type": "IconButton",
            "Action": {
                "PluginId": "BuilderTools",
                "DataModel": "Standalone",
                "ItemId": "Insert/ScrollingFrame",
                "Category": "Actions"
            }
        },
        {
            "Id": "2eb09fc8-6f45-42cf-92ac-de8c964ca8bf",
            "Type": "IconButton",
            "Action": {
                "PluginId": "BuilderTools",
                "DataModel": "Standalone",
                "Category": "Actions",
                "ItemId": "Insert/TextLabel"
            }
        },
        {
            "Id": "8a7c9283-420b-4fec-a9a9-1a3bedc6ed67",
            "Type": "IconButton",
            "Action": {
                "PluginId": "BuilderTools",
                "DataModel": "Standalone",
                "ItemId": "Insert/TextButton",
                "Category": "Actions"
            }
        },
        {
            "Id": "1cf6419e-55f3-4d10-a7f4-f10989c0e1e0",
            "Type": "IconButton",
            "Action": {
                "PluginId": "BuilderTools",
                "DataModel": "Standalone",
                "Category": "Actions",
                "ItemId": "Insert/TextBox"
            }
        },
        {
            "Id": "Input",
            "Type": "SplitButton",
            "Setting": {
                "PluginId": "BuilderTools",
                "DataModel": "Standalone",
                "Category": "Settings",
                "ItemId": "InsertUIInput"
            },
            "ShowSettingOptions": true
        },
        {
            "Id": "Label",
            "Type": "SplitButton",
            "Setting": {
                "PluginId": "BuilderTools",
                "DataModel": "Standalone",
                "Category": "Settings",
                "ItemId": "InsertUILabel"
            },
            "ShowSettingOptions": true
        },
        {
            "Type": "Separator",
            "Size": "Large"
        },
        {
            "Id": "ce30da2d-0821-43df-9103-3cde299adafb",
            "Type": "IconButton",
            "Action": {
                "PluginId": "StyleEditor",
                "DataModel": "Standalone",
                "Category": "Actions",
                "ItemId": "Toggle"
            }
        },
        {
            "Type": "Separator",
            "Size": "Large"
        },
        {
            "Id": "Appearance",
            "Type": "SplitButton",
            "Setting": {
                "PluginId": "BuilderTools",
                "DataModel": "Standalone",
                "Category": "Settings",
                "ItemId": "InsertUIAppearance"
            },
            "ShowSettingOptions": true
        },
        {
            "Id": "Layout",
            "Type": "SplitButton",
            "Setting": {
                "PluginId": "BuilderTools",
                "DataModel": "Standalone",
                "Category": "Settings",
                "ItemId": "InsertUILayout"
            },
            "ShowSettingOptions": true
        },
        {
            "Id": "Constraint",
            "Type": "SplitButton",
            "Setting": {
                "PluginId": "BuilderTools",
                "DataModel": "Standalone",
                "Category": "Settings",
                "ItemId": "InsertUIConstraint"
            },
            "ShowSettingOptions": true
        }
    ]
}